MANIFEST.in
README.md
setup.cfg
setup.py
unifyml/VERSION
unifyml/__init__.py
unifyml/_troubleshoot.py
unifyml/nn.py
unifyml.egg-info/PKG-INFO
unifyml.egg-info/SOURCES.txt
unifyml.egg-info/dependency_links.txt
unifyml.egg-info/requires.txt
unifyml.egg-info/top_level.txt
unifyml/backend/__init__.py
unifyml/backend/_backend.py
unifyml/backend/_dtype.py
unifyml/backend/_linalg.py
unifyml/backend/_linalg_preconditioner.py
unifyml/backend/_minimize.py
unifyml/backend/_numpy_backend.py
unifyml/backend/_object.py
unifyml/backend/_partition.py
unifyml/backend/_profile.py
unifyml/backend/_triangular_wip.py
unifyml/backend/jax/__init__.py
unifyml/backend/jax/_jax_backend.py
unifyml/backend/jax/stax_nets.py
unifyml/backend/tensorflow/__init__.py
unifyml/backend/tensorflow/_compile_cuda.py
unifyml/backend/tensorflow/_profiling.py
unifyml/backend/tensorflow/_tf_backend.py
unifyml/backend/tensorflow/_tf_cuda_resample.py
unifyml/backend/tensorflow/nets.py
unifyml/backend/torch/__init__.py
unifyml/backend/torch/_torch_backend.py
unifyml/backend/torch/nets.py
unifyml/math/__init__.py
unifyml/math/_fit.py
unifyml/math/_functional.py
unifyml/math/_magic_ops.py
unifyml/math/_nd.py
unifyml/math/_ops.py
unifyml/math/_optimize.py
unifyml/math/_shape.py
unifyml/math/_sparse.py
unifyml/math/_tensors.py
unifyml/math/_trace.py
unifyml/math/extrapolation.py
unifyml/math/magic.py